mseep_nebulagraph_mcp_server-1.0.0.dist-info/licenses/LICENSE
tests/__init__.py
tests/test_integration.py
mseep_nebulagraph_mcp_server-1.0.0.dist-info/METADATA
mseep_nebulagraph_mcp_server-1.0.0.dist-info/WHEEL
mseep_nebulagraph_mcp_server-1.0.0.dist-info/top_level.txt
mseep_nebulagraph_mcp_server-1.0.0.dist-info/RECORD
